{
  "slug": "extroverted-parent-introverted-child",
  "title": "The Extroverted Parent with an Introverted Child: Bridging the Gap",
  "metaDescription": "*TL;DR: You love your introverted child but feel like you’re speaking different languages. That’s not your fault.",
  "tldr": "TL;DR: You love your introverted child but feel like you’re speaking different languages. That’s not your fault. The gap between your high-energy social wiring and their need for quiet is very real. But it’s bridgeable. This article gives you practical, parent-tested moves to connect without forcing them to be like you. Stop trying to change their nature. Learn to meet them where they are.",
  "category": "Parents and Family",
  "tags": [
    "parenting",
    "temperament-mismatch"
  ],
  "angle": null,
  "status": "published",
  "queuedAt": 1778077110615,
  "publishedAt": 1778079555233,
  "dateModified": 1778091718147,
  "body": "# The Extroverted Parent with an Introverted Child: Bridging the Gap\n\n*TL;DR: You love your introverted child but feel like you’re speaking different languages. That’s not your fault. The gap between your high-energy social wiring and their need for quiet is very real. But it’s bridgeable. This article gives you practical, parent-tested moves to connect without forcing them to be like you. Stop trying to change their nature. Learn to meet them where they are.*\n\nLook, here’s the thing. You’re the parent who thrives on conversation, playdates, and family gatherings. Your child prefers the corner with a book, one friend at a time, and quiet. You love them. You want them to be happy. But their happiness doesn’t look like yours. And that terrifies you. You wonder: am I messing this up? Are they missing out? Is something wrong?\n\nStop overthinking this. Nothing is wrong. You have a temperament mismatch. It’s common. And fixable.\n\nI’m The Oracle Lover. I’m a researcher-parent who spends my days studying introverted, anxious, and highly sensitive school-age children. I’ve written for A Quiet Classroom because nobody handed me a manual when my extroverted self met my introverted son. Let me demystify this for you.\n\n## Why This Disconnect Happens\n\n### The Biology Behind the Behavior\n\nYour child’s nervous system is wired differently than yours. Elaine Aron’s research on highly sensitive people shows that introverted brains process stimulation more deeply. More googling is not needed here. It’s biology. Their autonomic nervous system reacts more strongly to noise, crowds, and social demands.\n\nYou see a birthday party full of fun. They see an overwhelming wall of sound, flashing lights, and unpredictable interactions. Their body says *too much*. Yours says *party time*.\n\nThis isn’t mystical. It’s mechanical. Their threshold for social input is lower. That’s not weakness. It’s a different set of factory settings.\n\n### Introversion Is Not Shyness. Anxiety Is Not Defiance. Know the Difference.\n\nIntroversion is a preference for lower stimulation. Shyness is fear of judgment. Anxiety is chronic worry. Defiance is resistance to authority. Your child can be introverted without being shy. They can be anxious without being defiant.\n\nToo many parents misread their child’s quiet refusal as opposition. “They just need to try harder.” No. That’s like telling a fish to fly. The school wasn’t built for your child. That’s not your child’s fault. Your job isn’t to make them fit a square hole. Your job is to be the bridge between their world and the extroverted one you inhabit.\n\n## Stop Trying to “Fix” Your Child\n\n### Acceptance Is the First Move\n\nYou already know the answer. You just don’t like it. Your child is not a project to improve. They are a person to understand.\n\nTherapists like Natasha Daniels and Ross Greene have shown that behavior is communication. When your child melts down after a playdate, they’re not being bratty. They’re overstimulated. When they refuse to join a team sport, they’re not lazy. They’re protecting their energy.\n\nYour job: stop interpreting their needs as failures. Start believing they have a valid reason.\n\n### The Danger of the “Fun Parent” Trap\n\nYou want to provide wonderful experiences. You push them to try things you loved as a kid. Scout camp. Dance class. Big birthday dinners. Each push feels like love.\n\nBut from their side? It feels like pressure. It feels like you don’t see them.\n\nI know a mom who spent three years forcing her son to attend every family reunion. She thought she was teaching him to love family. He spent those years hiding under the table with a fear of uncle jokes. The body doesn’t lie. The mind does. Constantly. Your child’s avoidance is honest. Listen.\n\n## Practical Bridges: Three Daily Shifts\n\n### Shift 1: Read Their Energy Before You Speak\n\nWalk in the door after school. Don’t ask: “How was your day? Who did you play with? What did you learn?”\n\nThat’s interrogation. Not connection.\n\nInstead, sit quietly beside them. Offer a snack. Wait. Let them initiate. Or better, say: “I’m glad you’re home. I’ll be in the kitchen if you want to talk later.”\n\nThe recharge time after school isn’t laziness. It’s biology. They’ve been “on” all day. They need to power down.\n\n**Here’s what actually works:** A ten-minute buffer of silence. No screens. No questions. Just low stimulation presence. You’ll be amazed what comes out once the pressure is off.\n\n### Shift 2: Schedule One-on-One Time That Matches Their Tempo\n\nYour child doesn’t need a weekend full of activities. They need you, fully present, in a low-key setting.\n\nTry this: Saturday morning, instead of rushing to a soccer game, take them to the library. Sit in the quiet section. Read together. Talk softly. No agenda.\n\nOr go for a walk at dusk. No destination. Just steps.\n\nThe extroverted parent wants to maximize time. The introverted child needs to minimize pressure. You can do both. It’s a dance, not a debate.\n\n### Shift 3: Rewrite the Social Script Together\n\nYou’re worried they don’t have friends. You see them alone at recess and your heart breaks. But they’re not lonely. They’re recharging.\n\nBut if they do want friends and struggle, you can help. Not by fixing them, but by practicing scripts.\n\nRole-play conversations. “What do you say when someone asks to play on the swings?” “How do you invite a classmate for a short playdate?”\n\nKeep it short. One skill at a time. Use humor. “Okay, now pretend I’m the most annoying kid in class. What do you say to get me to give you space?”\n\nLess theory. More practice.\n\nAlso: consider groups based on shared interests, not just social exposure. A Lego club. A book club. A nature club. Kids who don’t love small talk can bond over doing something.\n\n## When Social Situations Clash\n\n### Family Gatherings: Yours or Yours-in-Law\n\nYou love your family. Your child dreads the hugs, the loud aunties, the endless questions.\n\nMake a plan before you go. Decide together how long you’ll stay. Agree on a signal they can use if they’re overwhelmed. A touch to the nose. A hand on your arm. That means “I need a break.”\n\nYou can be their shield. Nobody’s coming to explain this to you. So I will. It’s okay to say to relatives: “He’s just warming up. He’ll come around when he’s ready.” Or: “We’re on a schedule tonight. Can’t stay late.”\n\nYou’re not rude. You’re protective. And protective is necessary.\n\n### School Events and Performances\n\nMany introverted kids hate being the center of attention. They’ll do the work. They just don’t want the spotlight.\n\nTalk to teachers. Ask if your child can have a behind-the-scenes role. Set up the sound. Hold the script. Help with costumes. Participation without performance.\n\nIf they have to be in the school play, practice at home with no audience first. Let them master the lines in private. Then add siblings. Then extended family. Slow exposure. Not shock therapy.\n\n## The Recharge Equation\n\n### Create a Sanctuary at Home\n\nHome must be the safest place. No forced social interaction. No surprises. No “surprise we have guests!” for an introverted child. That’s a nightmare.\n\nDesignate a quiet zone. Maybe their room. Maybe a corner with pillows. When they go there, nobody follows. No siblings allowed. No parents either. That is their bubble.\n\nYou can explain to other adults: “She’s introverted. She needs alone time to refuel. It’s not personal.”\n\n### The Cost of Over-Scheduling\n\nAn extroverted parent loves social events. You recharge by being around people. So you naturally fill the calendar.\n\nBut your child has a different battery. Every playdate, lesson, and party drains them. They need days with nothing planned. Literally nothing.\n\nTry this: One weekend day fully unscheduled. No activities. No errands. No playdates. Just open time at home. Watch what happens. They may read. Build. Talk to you. They will return to themselves.\n\nYou’ll lose the fear that they’re missing out. Because you’ll see them gain energy.\n\n## When You Need to Push (Yes, Sometimes)\n\nI’m not saying never encourage growth. Introverted kids do need to learn to navigate social situations. But the push must be gentle, respectful, and timed right.\n\nYou see your child avoid a new activity. Don’t force it. But don’t let them quit before trying. Offer a trial. “We go twice. If you really hate it, we stop. No guilt.”\n\nHold that promise. They need to trust you. If you break that trust, they’ll resist harder.\n\nYes, sometimes they need a nudge. But always with their input. Always with an exit plan. You are not their enemy. You are their coach.\n\n[helping anxious child try new activities](/articles/gifted-anxious-overlap-2e)\n\n## FAQ\n\n**Q: How do I explain my child’s introversion to relatives who don’t understand?**\n\nA: Keep it simple. “She’s wired for quiet. She likes people but in small doses. Please don’t take it personally when she needs space.” You don’t need to defend it. Just state it. Change the subject if they argue.\n\n**Q: Should I force my child to say hello or thank you at gatherings?**\n\nA: Yes, but with flexibility. Let them give a silent wave or a handshake, not a hug. Practice at home. But don’t demand eye contact or chatter. That’s performative, not real.\n\n**Q: My child refuses to try any new activity. How do I respond?**\n\nA: Listen to why. Is it fear of social anxiety? Or genuine disinterest? If it’s anxiety, do slow exposure. If it’s disinterest, trust their preference. You can’t make them love soccer, but you can find something they will love. Keep exploring.\n\n**Q: Is it normal to feel guilty as an extroverted parent?**\n\nA: Yes. Very normal. But guilt doesn’t help. Action does. You’re reading this. You’re trying. That already makes you one of the good ones.\n\n## Closing: Become the Bridge, Not the Buttress\n\nYou don’t have to become an introvert. You don’t have to speak softly or hate parties. You just have to build a bridge between your world and theirs.\n\nThat means slowing down. Listening more. Pushing less. Trusting that their quiet strength is real.\n\nI’ve seen so many families transform when an extroverted parent decides to stop fighting their child’s nature. The yelling stops. The tears stop. Connection starts.\n\nYou can do this. You can be the parent who really sees their child. Not the one who wishes they were different.\n\nFor more guidance, visit The Oracle Lover at [https://theoraclelover.com](https://theoraclelover.com). I write there about temperament, anxiety, and raising sensitive kids in a loud world. You’re not alone.\n\nAnd if you need more practical resources, check out [after-school routines for introverts](/articles/what-highly-sensitive-children-need-at-school) and [school advocacy for introverted children](/articles/what-highly-sensitive-children-need-at-school).\n\n*Lokah samastah sukhino bhavantu.*\n\n*Sat Chit Ananda.*\n",
  "readingTime": 8,
  "heroUrl": "https://quiet-classroom.b-cdn.net/heroes/extroverted-parent-introverted-child.webp",
  "ogImage": null,
  "heroAlt": "The Extroverted Parent with an Introverted Child: Bridging the Gap. Calm gradient hero for A Quiet Classroom."
}