{
  "slug": "introversion-vs-school-refusal--for-middle-school-parents",
  "title": "The Difference Between Introversion and School Refusal : for middle-school parents",
  "metaDescription": "",
  "tldr": "",
  "category": "School Life",
  "tags": [
    "school-refusal",
    "introversion"
  ],
  "angle": "for middle-school parents",
  "status": "queued",
  "queuedAt": 1778077110632,
  "publishedAt": null,
  "dateModified": null,
  "body": "",
  "readingTime": null,
  "heroUrl": null,
  "ogImage": null
}