{
  "slug": "sensory-accommodations-that-actually-help--for-a-kid-who-masks-at-school",
  "title": "Sensory Accommodations That Actually Help in Schools : for a kid who masks at school",
  "metaDescription": "",
  "tldr": "",
  "category": "Sensory and Environment",
  "tags": [
    "sensory",
    "accommodations"
  ],
  "angle": "for a kid who masks at school",
  "status": "queued",
  "queuedAt": 1778077110701,
  "publishedAt": null,
  "dateModified": null,
  "body": "",
  "readingTime": null,
  "heroUrl": null,
  "ogImage": null
}